.dockerignore
AUTHORS
ChangeLog
Dockerfile
LICENSE
README.md
requirements.txt
setup.cfg
setup.py
examples/__init__.py
examples/de_example.py
examples/ga_example.py
examples/pso_example.py
examples/worlds/circle.wd
examples/worlds/circles_asym.wd
kheppy/__init__.py
kheppy.egg-info/PKG-INFO
kheppy.egg-info/SOURCES.txt
kheppy.egg-info/dependency_links.txt
kheppy.egg-info/not-zip-safe
kheppy.egg-info/pbr.json
kheppy.egg-info/requires.txt
kheppy.egg-info/top_level.txt
kheppy/core/__init__.py
kheppy/core/constants.py
kheppy/core/simulation.py
kheppy/evocom/__init__.py
kheppy/evocom/commons/__init__.py
kheppy/evocom/commons/base.py
kheppy/evocom/commons/individual.py
kheppy/evocom/commons/nn.py
kheppy/evocom/commons/population.py
kheppy/evocom/de/__init__.py
kheppy/evocom/de/de.py
kheppy/evocom/de/individual.py
kheppy/evocom/de/population.py
kheppy/evocom/ga/__init__.py
kheppy/evocom/ga/ga.py
kheppy/evocom/ga/individual.py
kheppy/evocom/ga/population.py
kheppy/evocom/pso/__init__.py
kheppy/evocom/pso/individual.py
kheppy/evocom/pso/population.py
kheppy/evocom/pso/pso.py
kheppy/utils/__init__.py
kheppy/utils/fitfunc.py
kheppy/utils/misc.py
kheppy/utils/reporting.py