Metadata-Version: 2.1
Name: kheppy
Version: 0.1.0
Summary: Python API with evolutionary computation and reinforcement learning algorithms for Khepera simulation engine
Home-page: UNKNOWN
Author: Michal Augoff
License: MIT
Platform: UNKNOWN
